django_brouillons/README.md
django_brouillons/__init__.py
django_brouillons/admin.py
django_brouillons/exceptions.py
django_brouillons/locale/fr/LC_MESSAGES/django.mo
django_brouillons/locale/fr/LC_MESSAGES/django.po
django_brouillons/managers.py
django_brouillons/models.py
django_brouillons/queries.py
django_brouillons/templates/admin/submit_line.html
django_brouillons-0.3.0.dist-info/METADATA
django_brouillons-0.3.0.dist-info/WHEEL
django_brouillons-0.3.0.dist-info/licenses/AUTHORS.md
django_brouillons-0.3.0.dist-info/licenses/LICENSE
django_brouillons-0.3.0.dist-info/RECORD
