Metadata-Version: 2.4
Name: django-brouillons
Version: 0.3.0
Summary: Handle django models drafts and published states
License: GNU GPLv3
License-File: AUTHORS.md
License-File: LICENSE
Author: Kapt dev team
Author-email: dev@kapt.mobi
Requires-Python: >=3.10
Classifier: License :: Other/Proprietary License
Classifier: Programming Language :: Python :: 3
Classifier: Programming Language :: Python :: 3.10
Classifier: Programming Language :: Python :: 3.11
Classifier: Programming Language :: Python :: 3.12
Classifier: Programming Language :: Python :: 3.13
Classifier: Programming Language :: Python :: 3.14
Requires-Dist: Django (>=3.2)
Requires-Dist: django-clone (>=5.3.3,<6.0.0)
Project-URL: Repository, https://gitlab.com/kapt/open-source/django-brouillons
